{
    "students": [
        {
            "id": 1,
            "firstName": "Joseph",
            "lastName": "Brown",
            "gender": "Male",
            "email": "joseph.brown_1@university.edu",
            "dateOfBirth": "1987-01-17",
            "age": 37,
            "major": "International Relations",
            "university": "Tech Institute",
            "graduationYear": 2025,
            "gpa": 3.66,
            "creditHours": 68,
            "isInternational": true,
            "scholarshipRecipient": true,
            "phoneNumber": "(240) 394-7033"
        },
        {
            "id": 2,
            "firstName": "Charles",
            "lastName": "Martinez",
            "gender": "Male",
            "email": "charles.martinez_2@university.edu",
            "dateOfBirth": "1982-06-28",
            "age": 42,
            "major": "International Relations",
            "university": "Central University",
            "graduationYear": 2025,
            "gpa": 2.57,
            "creditHours": 95,
            "isInternational": true,
            "scholarshipRecipient": true,
            "phoneNumber": "(239) 971-2292"
        },
        {
            "id": 3,
            "firstName": "Jennifer",
            "lastName": "Taylor",
            "gender": "Female",
            "email": "jennifer.taylor_3@university.edu",
            "dateOfBirth": "1985-02-15",
            "age": 39,
            "major": "Biology",
            "university": "Innovation Institute",
            "graduationYear": 2025,
            "gpa": 2.89,
            "creditHours": 118,
            "isInternational": false,
            "scholarshipRecipient": true,
            "phoneNumber": "(740) 693-7603"
        },
        {
            "id": 4,
            "firstName": "Daniel",
            "lastName": "Davis",
            "gender": "Male",
            "email": "daniel.davis_4@university.edu",
            "dateOfBirth": "1983-02-28",
            "age": 41,
            "major": "Communications",
            "university": "Liberal Arts College",
            "graduationYear": 2027,
            "gpa": 3.81,
            "creditHours": 105,
            "isInternational": true,
            "scholarshipRecipient": false,
            "phoneNumber": "(812) 421-3166"
        },
        {
            "id": 5,
            "firstName": "Anthony",
            "lastName": "Martin",
            "gender": "Male",
            "email": "anthony.martin_5@university.edu",
            "dateOfBirth": "1981-09-03",
            "age": 43,
            "major": "Graphic Design",
            "university": "Metropolitan University",
            "graduationYear": 2027,
            "gpa": 3.71,
            "creditHours": 73,
            "isInternational": true,
            "scholarshipRecipient": false,
            "phoneNumber": "(910) 112-6594"
        },
        {
            "id": 6,
            "firstName": "Michelle",
            "lastName": "Miller",
            "gender": "Female",
            "email": "michelle.miller_6@university.edu",
            "dateOfBirth": "1987-11-06",
            "age": 37,
            "major": "Communications",
            "university": "Innovation Institute",
            "graduationYear": 2027,
            "gpa": 3.96,
            "creditHours": 43,
            "isInternational": false,
            "scholarshipRecipient": true,
            "phoneNumber": "(414) 841-3962"
        },
        {
            "id": 7,
            "firstName": "Jessica",
            "lastName": "Martin",
            "gender": "Female",
            "email": "jessica.martin_7@university.edu",
            "dateOfBirth": "1988-06-06",
            "age": 36,
            "major": "Physics",
            "university": "Northern College",
            "graduationYear": 2028,
            "gpa": 2.88,
            "creditHours": 95,
            "isInternational": true,
            "scholarshipRecipient": true,
            "phoneNumber": "(628) 471-2126"
        },
        {
            "id": 8,
            "firstName": "Donald",
            "lastName": "Miller",
            "gender": "Male",
            "email": "donald.miller_8@university.edu",
            "dateOfBirth": "1986-05-23",
            "age": 38,
            "major": "Political Science",
            "university": "Mountain View University",
            "graduationYear": 2024,
            "gpa": 3.82,
            "creditHours": 116,
            "isInternational": false,
            "scholarshipRecipient": false,
            "phoneNumber": "(830) 186-1951"
        },
        {
            "id": 9,
            "firstName": "Kimberly",
            "lastName": "Smith",
            "gender": "Female",
            "email": "kimberly.smith_9@university.edu",
            "dateOfBirth": "1984-09-24",
            "age": 40,
            "major": "Computer Science",
            "university": "Mountain View University",
            "graduationYear": 2024,
            "gpa": 2.92,
            "creditHours": 80,
            "isInternational": true,
            "scholarshipRecipient": false,
            "phoneNumber": "(575) 937-8765"
        },
        {
            "id": 10,
            "firstName": "Karen",
            "lastName": "Jones",
            "gender": "Female",
            "email": "karen.jones_10@university.edu",
            "dateOfBirth": "1988-12-13",
            "age": 36,
            "major": "Graphic Design",
            "university": "Northern College",
            "graduationYear": 2025,
            "gpa": 3.62,
            "creditHours": 56,
            "isInternational": false,
            "scholarshipRecipient": false,
            "phoneNumber": "(542) 834-8908"
        },
        {
            "id": 11,
            "firstName": "John",
            "lastName": "Brown",
            "gender": "Male",
            "email": "john.brown_11@university.edu",
            "dateOfBirth": "1985-11-08",
            "age": 39,
            "major": "Environmental Science",
            "university": "Global University",
            "graduationYear": 2026,
            "gpa": 2.55,
            "creditHours": 50,
            "isInternational": true,
            "scholarshipRecipient": true,
            "phoneNumber": "(981) 636-8784"
        },
        {
            "id": 12,
            "firstName": "Karen",
            "lastName": "Williams",
            "gender": "Female",
            "email": "karen.williams_12@university.edu",
            "dateOfBirth": "1983-10-23",
            "age": 41,
            "major": "Mathematics",
            "university": "Liberal Arts College",
            "graduationYear": 2026,
            "gpa": 2.68,
            "creditHours": 90,
            "isInternational": true,
            "scholarshipRecipient": false,
            "phoneNumber": "(833) 468-6267"
        },
        {
            "id": 13,
            "firstName": "Margaret",
            "lastName": "Miller",
            "gender": "Female",
            "email": "margaret.miller_13@university.edu",
            "dateOfBirth": "1982-11-13",
            "age": 42,
            "major": "Computer Science",
            "university": "Innovation Institute",
            "graduationYear": 2028,
            "gpa": 3.24,
            "creditHours": 94,
            "isInternational": false,
            "scholarshipRecipient": false,
            "phoneNumber": "(805) 468-8247"
        },
        {
            "id": 14,
            "firstName": "John",
            "lastName": "Davis",
            "gender": "Male",
            "email": "john.davis_14@university.edu",
            "dateOfBirth": "1988-02-13",
            "age": 36,
            "major": "International Relations",
            "university": "Coastal State College",
            "graduationYear": 2026,
            "gpa": 3.69,
            "creditHours": 114,
            "isInternational": false,
            "scholarshipRecipient": false,
            "phoneNumber": "(378) 280-4993"
        },
        {
            "id": 15,
            "firstName": "Jennifer",
            "lastName": "Williams",
            "gender": "Female",
            "email": "jennifer.williams_15@university.edu",
            "dateOfBirth": "1983-05-27",
            "age": 41,
            "major": "Environmental Science",
            "university": "Metropolitan University",
            "graduationYear": 2026,
            "gpa": 3.89,
            "creditHours": 96,
            "isInternational": false,
            "scholarshipRecipient": false,
            "phoneNumber": "(288) 906-6251"
        },
        {
            "id": 16,
            "firstName": "Paul",
            "lastName": "Hernandez",
            "gender": "Male",
            "email": "paul.hernandez_16@university.edu",
            "dateOfBirth": "1983-09-07",
            "age": 41,
            "major": "Psychology",
            "university": "Central University",
            "graduationYear": 2026,
            "gpa": 2.51,
            "creditHours": 88,
            "isInternational": false,
            "scholarshipRecipient": true,
            "phoneNumber": "(399) 840-2400"
        },
        {
            "id": 17,
            "firstName": "Elizabeth",
            "lastName": "Moore",
            "gender": "Female",
            "email": "elizabeth.moore_17@university.edu",
            "dateOfBirth": "1986-06-01",
            "age": 38,
            "major": "Nursing",
            "university": "Mountain View University",
            "graduationYear": 2026,
            "gpa": 3.47,
            "creditHours": 101,
            "isInternational": true,
            "scholarshipRecipient": false,
            "phoneNumber": "(643) 517-1906"
        },
        {
            "id": 18,
            "firstName": "James",
            "lastName": "Martin",
            "gender": "Male",
            "email": "james.martin_18@university.edu",
            "dateOfBirth": "1988-06-18",
            "age": 36,
            "major": "Political Science",
            "university": "Northern College",
            "graduationYear": 2027,
            "gpa": 2.75,
            "creditHours": 94,
            "isInternational": true,
            "scholarshipRecipient": false,
            "phoneNumber": "(493) 387-9139"
        },
        {
            "id": 19,
            "firstName": "Barbara",
            "lastName": "Wilson",
            "gender": "Female",
            "email": "barbara.wilson_19@university.edu",
            "dateOfBirth": "1982-02-13",
            "age": 42,
            "major": "Computer Science",
            "university": "Central University",
            "graduationYear": 2028,
            "gpa": 3.17,
            "creditHours": 54,
            "isInternational": false,
            "scholarshipRecipient": true,
            "phoneNumber": "(210) 794-4417"
        },
        {
            "id": 20,
            "firstName": "Paul",
            "lastName": "Thompson",
            "gender": "Male",
            "email": "paul.thompson_20@university.edu",
            "dateOfBirth": "1981-08-19",
            "age": 43,
            "major": "Electrical Engineering",
            "university": "Central University",
            "graduationYear": 2028,
            "gpa": 2.83,
            "creditHours": 119,
            "isInternational": true,
            "scholarshipRecipient": true,
            "phoneNumber": "(969) 411-3801"
        },
        {
            "id": 21,
            "firstName": "Linda",
            "lastName": "Garcia",
            "gender": "Female",
            "email": "linda.garcia_21@university.edu",
            "dateOfBirth": "1987-09-04",
            "age": 37,
            "major": "Computer Science",
            "university": "State University",
            "graduationYear": 2024,
            "gpa": 2.99,
            "creditHours": 97,
            "isInternational": true,
            "scholarshipRecipient": true,
            "phoneNumber": "(312) 507-2007"
        },
        {
            "id": 22,
            "firstName": "Susan",
            "lastName": "Johnson",
            "gender": "Female",
            "email": "susan.johnson_22@university.edu",
            "dateOfBirth": "1988-10-25",
            "age": 36,
            "major": "Psychology",
            "university": "Tech Institute",
            "graduationYear": 2028,
            "gpa": 2.72,
            "creditHours": 35,
            "isInternational": true,
            "scholarshipRecipient": true,
            "phoneNumber": "(519) 815-7839"
        },
        {
            "id": 23,
            "firstName": "Michael",
            "lastName": "Martin",
            "gender": "Male",
            "email": "michael.martin_23@university.edu",
            "dateOfBirth": "1988-12-26",
            "age": 36,
            "major": "Political Science",
            "university": "Global University",
            "graduationYear": 2026,
            "gpa": 2.54,
            "creditHours": 105,
            "isInternational": false,
            "scholarshipRecipient": false,
            "phoneNumber": "(745) 733-6420"
        },
        {
            "id": 24,
            "firstName": "Daniel",
            "lastName": "Jones",
            "gender": "Male",
            "email": "daniel.jones_24@university.edu",
            "dateOfBirth": "1983-10-19",
            "age": 41,
            "major": "Marketing",
            "university": "Northern College",
            "graduationYear": 2025,
            "gpa": 3.51,
            "creditHours": 67,
            "isInternational": false,
            "scholarshipRecipient": false,
            "phoneNumber": "(415) 952-5584"
        },
        {
            "id": 25,
            "firstName": "Thomas",
            "lastName": "White",
            "gender": "Male",
            "email": "thomas.white_25@university.edu",
            "dateOfBirth": "1984-06-13",
            "age": 40,
            "major": "Business Administration",
            "university": "Mountain View University",
            "graduationYear": 2025,
            "gpa": 3.18,
            "creditHours": 32,
            "isInternational": true,
            "scholarshipRecipient": false,
            "phoneNumber": "(341) 917-3511"
        },
        {
            "id": 26,
            "firstName": "Elizabeth",
            "lastName": "Rodriguez",
            "gender": "Female",
            "email": "elizabeth.rodriguez_26@university.edu",
            "dateOfBirth": "1982-02-14",
            "age": 42,
            "major": "Psychology",
            "university": "State University",
            "graduationYear": 2025,
            "gpa": 3.86,
            "creditHours": 101,
            "isInternational": true,
            "scholarshipRecipient": false,
            "phoneNumber": "(943) 395-8584"
        },
        {
            "id": 27,
            "firstName": "Michael",
            "lastName": "Davis",
            "gender": "Male",
            "email": "michael.davis_27@university.edu",
            "dateOfBirth": "1985-06-28",
            "age": 39,
            "major": "Communications",
            "university": "Liberal Arts College",
            "graduationYear": 2025,
            "gpa": 2.7,
            "creditHours": 97,
            "isInternational": false,
            "scholarshipRecipient": false,
            "phoneNumber": "(389) 814-3702"
        },
        {
            "id": 28,
            "firstName": "Betty",
            "lastName": "Moore",
            "gender": "Female",
            "email": "betty.moore_28@university.edu",
            "dateOfBirth": "1985-06-28",
            "age": 39,
            "major": "Electrical Engineering",
            "university": "Northern College",
            "graduationYear": 2028,
            "gpa": 3.97,
            "creditHours": 104,
            "isInternational": false,
            "scholarshipRecipient": false,
            "phoneNumber": "(243) 411-8212"
        },
        {
            "id": 29,
            "firstName": "Jessica",
            "lastName": "Davis",
            "gender": "Female",
            "email": "jessica.davis_29@university.edu",
            "dateOfBirth": "1987-02-04",
            "age": 37,
            "major": "Engineering",
            "university": "Global University",
            "graduationYear": 2026,
            "gpa": 3.08,
            "creditHours": 74,
            "isInternational": true,
            "scholarshipRecipient": true,
            "phoneNumber": "(376) 646-2739"
        },
        {
            "id": 30,
            "firstName": "Elizabeth",
            "lastName": "Hernandez",
            "gender": "Female",
            "email": "elizabeth.hernandez_30@university.edu",
            "dateOfBirth": "1983-05-08",
            "age": 41,
            "major": "Nursing",
            "university": "Mountain View University",
            "graduationYear": 2028,
            "gpa": 2.79,
            "creditHours": 35,
            "isInternational": true,
            "scholarshipRecipient": false,
            "phoneNumber": "(887) 393-8191"
        },
        {
            "id": 31,
            "firstName": "Mark",
            "lastName": "Johnson",
            "gender": "Male",
            "email": "mark.johnson_31@university.edu",
            "dateOfBirth": "1988-07-14",
            "age": 36,
            "major": "Psychology",
            "university": "Mountain View University",
            "graduationYear": 2024,
            "gpa": 3.07,
            "creditHours": 105,
            "isInternational": false,
            "scholarshipRecipient": true,
            "phoneNumber": "(334) 541-9249"
        },
        {
            "id": 32,
            "firstName": "David",
            "lastName": "Davis",
            "gender": "Male",
            "email": "david.davis_32@university.edu",
            "dateOfBirth": "1985-10-22",
            "age": 39,
            "major": "International Relations",
            "university": "Innovation Institute",
            "graduationYear": 2028,
            "gpa": 3.43,
            "creditHours": 89,
            "isInternational": true,
            "scholarshipRecipient": false,
            "phoneNumber": "(228) 538-9945"
        },
        {
            "id": 33,
            "firstName": "Steven",
            "lastName": "Thomas",
            "gender": "Male",
            "email": "steven.thomas_33@university.edu",
            "dateOfBirth": "1984-06-02",
            "age": 40,
            "major": "Environmental Science",
            "university": "Metropolitan University",
            "graduationYear": 2025,
            "gpa": 3.37,
            "creditHours": 99,
            "isInternational": true,
            "scholarshipRecipient": false,
            "phoneNumber": "(914) 963-9995"
        },
        {
            "id": 34,
            "firstName": "William",
            "lastName": "White",
            "gender": "Male",
            "email": "william.white_34@university.edu",
            "dateOfBirth": "1987-12-20",
            "age": 37,
            "major": "Biology",
            "university": "Liberal Arts College",
            "graduationYear": 2025,
            "gpa": 3.7,
            "creditHours": 81,
            "isInternational": true,
            "scholarshipRecipient": true,
            "phoneNumber": "(769) 179-6712"
        },
        {
            "id": 35,
            "firstName": "Andrew",
            "lastName": "Williams",
            "gender": "Male",
            "email": "andrew.williams_35@university.edu",
            "dateOfBirth": "1981-08-23",
            "age": 43,
            "major": "Mechanical Engineering",
            "university": "Liberal Arts College",
            "graduationYear": 2028,
            "gpa": 2.71,
            "creditHours": 86,
            "isInternational": true,
            "scholarshipRecipient": false,
            "phoneNumber": "(810) 156-3213"
        },
        {
            "id": 36,
            "firstName": "Matthew",
            "lastName": "Brown",
            "gender": "Male",
            "email": "matthew.brown_36@university.edu",
            "dateOfBirth": "1983-07-06",
            "age": 41,
            "major": "International Relations",
            "university": "Global University",
            "graduationYear": 2024,
            "gpa": 3.44,
            "creditHours": 76,
            "isInternational": false,
            "scholarshipRecipient": true,
            "phoneNumber": "(872) 393-6846"
        },
        {
            "id": 37,
            "firstName": "Nancy",
            "lastName": "Rodriguez",
            "gender": "Female",
            "email": "nancy.rodriguez_37@university.edu",
            "dateOfBirth": "1982-08-01",
            "age": 42,
            "major": "Political Science",
            "university": "Northern College",
            "graduationYear": 2026,
            "gpa": 3.12,
            "creditHours": 102,
            "isInternational": false,
            "scholarshipRecipient": true,
            "phoneNumber": "(713) 228-7859"
        },
        {
            "id": 38,
            "firstName": "Matthew",
            "lastName": "Thomas",
            "gender": "Male",
            "email": "matthew.thomas_38@university.edu",
            "dateOfBirth": "1984-05-03",
            "age": 40,
            "major": "Physics",
            "university": "Central University",
            "graduationYear": 2028,
            "gpa": 3.63,
            "creditHours": 116,
            "isInternational": false,
            "scholarshipRecipient": true,
            "phoneNumber": "(205) 247-2686"
        },
        {
            "id": 39,
            "firstName": "Mary",
            "lastName": "Williams",
            "gender": "Female",
            "email": "mary.williams_39@university.edu",
            "dateOfBirth": "1985-03-01",
            "age": 39,
            "major": "Physics",
            "university": "Central University",
            "graduationYear": 2024,
            "gpa": 3.53,
            "creditHours": 64,
            "isInternational": false,
            "scholarshipRecipient": true,
            "phoneNumber": "(563) 236-1822"
        },
        {
            "id": 40,
            "firstName": "Thomas",
            "lastName": "Thomas",
            "gender": "Male",
            "email": "thomas.thomas_40@university.edu",
            "dateOfBirth": "1984-10-03",
            "age": 40,
            "major": "Mechanical Engineering",
            "university": "Metropolitan University",
            "graduationYear": 2025,
            "gpa": 2.89,
            "creditHours": 105,
            "isInternational": false,
            "scholarshipRecipient": true,
            "phoneNumber": "(275) 457-1063"
        },
        {
            "id": 41,
            "firstName": "Donald",
            "lastName": "Martin",
            "gender": "Male",
            "email": "donald.martin_41@university.edu",
            "dateOfBirth": "1982-11-02",
            "age": 42,
            "major": "Environmental Science",
            "university": "Coastal State College",
            "graduationYear": 2025,
            "gpa": 2.81,
            "creditHours": 55,
            "isInternational": true,
            "scholarshipRecipient": false,
            "phoneNumber": "(943) 258-2185"
        },
        {
            "id": 42,
            "firstName": "Margaret",
            "lastName": "Williams",
            "gender": "Female",
            "email": "margaret.williams_42@university.edu",
            "dateOfBirth": "1984-04-12",
            "age": 40,
            "major": "International Relations",
            "university": "Coastal State College",
            "graduationYear": 2025,
            "gpa": 3.18,
            "creditHours": 81,
            "isInternational": false,
            "scholarshipRecipient": true,
            "phoneNumber": "(475) 710-6354"
        },
        {
            "id": 43,
            "firstName": "Nancy",
            "lastName": "Martin",
            "gender": "Female",
            "email": "nancy.martin_43@university.edu",
            "dateOfBirth": "1986-01-27",
            "age": 38,
            "major": "Mechanical Engineering",
            "university": "State University",
            "graduationYear": 2026,
            "gpa": 3.8,
            "creditHours": 42,
            "isInternational": false,
            "scholarshipRecipient": false,
            "phoneNumber": "(810) 167-6100"
        },
        {
            "id": 44,
            "firstName": "Linda",
            "lastName": "Jones",
            "gender": "Female",
            "email": "linda.jones_44@university.edu",
            "dateOfBirth": "1983-06-25",
            "age": 41,
            "major": "Graphic Design",
            "university": "Liberal Arts College",
            "graduationYear": 2024,
            "gpa": 3.23,
            "creditHours": 113,
            "isInternational": false,
            "scholarshipRecipient": false,
            "phoneNumber": "(786) 925-4363"
        },
        {
            "id": 45,
            "firstName": "Anthony",
            "lastName": "Moore",
            "gender": "Male",
            "email": "anthony.moore_45@university.edu",
            "dateOfBirth": "1985-10-08",
            "age": 39,
            "major": "International Relations",
            "university": "State University",
            "graduationYear": 2027,
            "gpa": 2.83,
            "creditHours": 59,
            "isInternational": false,
            "scholarshipRecipient": true,
            "phoneNumber": "(244) 119-8821"
        },
        {
            "id": 46,
            "firstName": "Mark",
            "lastName": "Hernandez",
            "gender": "Male",
            "email": "mark.hernandez_46@university.edu",
            "dateOfBirth": "1982-02-12",
            "age": 42,
            "major": "Engineering",
            "university": "Innovation Institute",
            "graduationYear": 2024,
            "gpa": 3.32,
            "creditHours": 78,
            "isInternational": true,
            "scholarshipRecipient": true,
            "phoneNumber": "(795) 550-9945"
        },
        {
            "id": 47,
            "firstName": "Matthew",
            "lastName": "Brown",
            "gender": "Male",
            "email": "matthew.brown_47@university.edu",
            "dateOfBirth": "1986-12-09",
            "age": 38,
            "major": "Environmental Science",
            "university": "Tech Institute",
            "graduationYear": 2028,
            "gpa": 2.64,
            "creditHours": 89,
            "isInternational": false,
            "scholarshipRecipient": false,
            "phoneNumber": "(772) 530-2791"
        },
        {
            "id": 48,
            "firstName": "Betty",
            "lastName": "Moore",
            "gender": "Female",
            "email": "betty.moore_48@university.edu",
            "dateOfBirth": "1983-10-12",
            "age": 41,
            "major": "Political Science",
            "university": "Coastal State College",
            "graduationYear": 2027,
            "gpa": 3.03,
            "creditHours": 111,
            "isInternational": true,
            "scholarshipRecipient": false,
            "phoneNumber": "(599) 252-8364"
        },
        {
            "id": 49,
            "firstName": "Betty",
            "lastName": "Martin",
            "gender": "Female",
            "email": "betty.martin_49@university.edu",
            "dateOfBirth": "1982-04-04",
            "age": 42,
            "major": "Nursing",
            "university": "Mountain View University",
            "graduationYear": 2027,
            "gpa": 3.29,
            "creditHours": 65,
            "isInternational": false,
            "scholarshipRecipient": false,
            "phoneNumber": "(700) 934-2870"
        },
        {
            "id": 50,
            "firstName": "Paul",
            "lastName": "Thompson",
            "gender": "Male",
            "email": "paul.thompson_50@university.edu",
            "dateOfBirth": "1984-05-10",
            "age": 40,
            "major": "Economics",
            "university": "Coastal State College",
            "graduationYear": 2027,
            "gpa": 2.57,
            "creditHours": 37,
            "isInternational": true,
            "scholarshipRecipient": false,
            "phoneNumber": "(243) 381-7923"
        },
        {
            "id": 51,
            "firstName": "Barbara",
            "lastName": "Jackson",
            "gender": "Female",
            "email": "barbara.jackson_51@university.edu",
            "dateOfBirth": "1988-10-23",
            "age": 36,
            "major": "Electrical Engineering",
            "university": "Mountain View University",
            "graduationYear": 2028,
            "gpa": 3.03,
            "creditHours": 57,
            "isInternational": true,
            "scholarshipRecipient": true,
            "phoneNumber": "(801) 257-6439"
        },
        {
            "id": 52,
            "firstName": "George",
            "lastName": "Hernandez",
            "gender": "Male",
            "email": "george.hernandez_52@university.edu",
            "dateOfBirth": "1987-06-07",
            "age": 37,
            "major": "Data Science",
            "university": "Mountain View University",
            "graduationYear": 2024,
            "gpa": 2.89,
            "creditHours": 36,
            "isInternational": true,
            "scholarshipRecipient": false,
            "phoneNumber": "(836) 531-4669"
        },
        {
            "id": 53,
            "firstName": "Emily",
            "lastName": "Jackson",
            "gender": "Female",
            "email": "emily.jackson_53@university.edu",
            "dateOfBirth": "1983-08-22",
            "age": 41,
            "major": "Engineering",
            "university": "Global University",
            "graduationYear": 2026,
            "gpa": 3.08,
            "creditHours": 91,
            "isInternational": true,
            "scholarshipRecipient": true,
            "phoneNumber": "(233) 237-6845"
        },
        {
            "id": 54,
            "firstName": "Charles",
            "lastName": "Brown",
            "gender": "Male",
            "email": "charles.brown_54@university.edu",
            "dateOfBirth": "1987-08-25",
            "age": 37,
            "major": "Nursing",
            "university": "Mountain View University",
            "graduationYear": 2025,
            "gpa": 3.2,
            "creditHours": 109,
            "isInternational": false,
            "scholarshipRecipient": false,
            "phoneNumber": "(758) 852-6536"
        },
        {
            "id": 55,
            "firstName": "Charles",
            "lastName": "Hernandez",
            "gender": "Male",
            "email": "charles.hernandez_55@university.edu",
            "dateOfBirth": "1982-05-17",
            "age": 42,
            "major": "Biology",
            "university": "Coastal State College",
            "graduationYear": 2026,
            "gpa": 3.54,
            "creditHours": 36,
            "isInternational": false,
            "scholarshipRecipient": true,
            "phoneNumber": "(443) 403-7899"
        },
        {
            "id": 56,
            "firstName": "Mary",
            "lastName": "Thomas",
            "gender": "Female",
            "email": "mary.thomas_56@university.edu",
            "dateOfBirth": "1982-02-26",
            "age": 42,
            "major": "Business Administration",
            "university": "Innovation Institute",
            "graduationYear": 2025,
            "gpa": 3.1,
            "creditHours": 90,
            "isInternational": true,
            "scholarshipRecipient": false,
            "phoneNumber": "(632) 451-5936"
        },
        {
            "id": 57,
            "firstName": "Susan",
            "lastName": "Davis",
            "gender": "Female",
            "email": "susan.davis_57@university.edu",
            "dateOfBirth": "1983-04-21",
            "age": 41,
            "major": "Physics",
            "university": "Mountain View University",
            "graduationYear": 2027,
            "gpa": 3.34,
            "creditHours": 71,
            "isInternational": true,
            "scholarshipRecipient": false,
            "phoneNumber": "(994) 913-3361"
        },
        {
            "id": 58,
            "firstName": "Margaret",
            "lastName": "Jones",
            "gender": "Female",
            "email": "margaret.jones_58@university.edu",
            "dateOfBirth": "1988-09-20",
            "age": 36,
            "major": "Computer Science",
            "university": "Tech Institute",
            "graduationYear": 2027,
            "gpa": 2.6,
            "creditHours": 104,
            "isInternational": false,
            "scholarshipRecipient": true,
            "phoneNumber": "(809) 999-6287"
        },
        {
            "id": 59,
            "firstName": "Susan",
            "lastName": "Hernandez",
            "gender": "Female",
            "email": "susan.hernandez_59@university.edu",
            "dateOfBirth": "1983-12-19",
            "age": 41,
            "major": "Biology",
            "university": "Central University",
            "graduationYear": 2028,
            "gpa": 2.6,
            "creditHours": 70,
            "isInternational": false,
            "scholarshipRecipient": true,
            "phoneNumber": "(739) 204-1701"
        },
        {
            "id": 60,
            "firstName": "Mark",
            "lastName": "Anderson",
            "gender": "Male",
            "email": "mark.anderson_60@university.edu",
            "dateOfBirth": "1982-06-12",
            "age": 42,
            "major": "Environmental Science",
            "university": "Liberal Arts College",
            "graduationYear": 2026,
            "gpa": 3.05,
            "creditHours": 103,
            "isInternational": true,
            "scholarshipRecipient": false,
            "phoneNumber": "(272) 540-7219"
        },
        {
            "id": 61,
            "firstName": "Linda",
            "lastName": "Thomas",
            "gender": "Female",
            "email": "linda.thomas_61@university.edu",
            "dateOfBirth": "1982-07-20",
            "age": 42,
            "major": "Political Science",
            "university": "Mountain View University",
            "graduationYear": 2028,
            "gpa": 3.38,
            "creditHours": 102,
            "isInternational": true,
            "scholarshipRecipient": false,
            "phoneNumber": "(270) 892-6749"
        },
        {
            "id": 62,
            "firstName": "Emily",
            "lastName": "Johnson",
            "gender": "Female",
            "email": "emily.johnson_62@university.edu",
            "dateOfBirth": "1984-12-09",
            "age": 40,
            "major": "Communications",
            "university": "Tech Institute",
            "graduationYear": 2027,
            "gpa": 3.95,
            "creditHours": 34,
            "isInternational": false,
            "scholarshipRecipient": false,
            "phoneNumber": "(290) 996-8956"
        },
        {
            "id": 63,
            "firstName": "Donald",
            "lastName": "Davis",
            "gender": "Male",
            "email": "donald.davis_63@university.edu",
            "dateOfBirth": "1984-09-17",
            "age": 40,
            "major": "Communications",
            "university": "Northern College",
            "graduationYear": 2025,
            "gpa": 2.89,
            "creditHours": 61,
            "isInternational": false,
            "scholarshipRecipient": false,
            "phoneNumber": "(763) 320-7633"
        },
        {
            "id": 64,
            "firstName": "George",
            "lastName": "Jackson",
            "gender": "Male",
            "email": "george.jackson_64@university.edu",
            "dateOfBirth": "1986-05-23",
            "age": 38,
            "major": "Psychology",
            "university": "Metropolitan University",
            "graduationYear": 2026,
            "gpa": 3.02,
            "creditHours": 103,
            "isInternational": true,
            "scholarshipRecipient": true,
            "phoneNumber": "(393) 556-1895"
        },
        {
            "id": 65,
            "firstName": "Robert",
            "lastName": "Smith",
            "gender": "Male",
            "email": "robert.smith_65@university.edu",
            "dateOfBirth": "1986-08-15",
            "age": 38,
            "major": "Marketing",
            "university": "Metropolitan University",
            "graduationYear": 2028,
            "gpa": 3.42,
            "creditHours": 32,
            "isInternational": false,
            "scholarshipRecipient": false,
            "phoneNumber": "(938) 914-2407"
        },
        {
            "id": 66,
            "firstName": "Susan",
            "lastName": "Thompson",
            "gender": "Female",
            "email": "susan.thompson_66@university.edu",
            "dateOfBirth": "1981-06-14",
            "age": 43,
            "major": "Economics",
            "university": "Liberal Arts College",
            "graduationYear": 2026,
            "gpa": 3.19,
            "creditHours": 113,
            "isInternational": false,
            "scholarshipRecipient": true,
            "phoneNumber": "(613) 620-1120"
        },
        {
            "id": 67,
            "firstName": "Carol",
            "lastName": "Garcia",
            "gender": "Female",
            "email": "carol.garcia_67@university.edu",
            "dateOfBirth": "1981-05-17",
            "age": 43,
            "major": "Mathematics",
            "university": "Mountain View University",
            "graduationYear": 2026,
            "gpa": 3.26,
            "creditHours": 64,
            "isInternational": false,
            "scholarshipRecipient": true,
            "phoneNumber": "(881) 992-8708"
        },
        {
            "id": 68,
            "firstName": "Robert",
            "lastName": "Thompson",
            "gender": "Male",
            "email": "robert.thompson_68@university.edu",
            "dateOfBirth": "1982-12-05",
            "age": 42,
            "major": "International Relations",
            "university": "Northern College",
            "graduationYear": 2024,
            "gpa": 2.56,
            "creditHours": 82,
            "isInternational": true,
            "scholarshipRecipient": true,
            "phoneNumber": "(694) 320-1870"
        },
        {
            "id": 69,
            "firstName": "Steven",
            "lastName": "Thomas",
            "gender": "Male",
            "email": "steven.thomas_69@university.edu",
            "dateOfBirth": "1981-10-11",
            "age": 43,
            "major": "Business Administration",
            "university": "Central University",
            "graduationYear": 2025,
            "gpa": 2.83,
            "creditHours": 40,
            "isInternational": false,
            "scholarshipRecipient": true,
            "phoneNumber": "(578) 767-6873"
        },
        {
            "id": 70,
            "firstName": "Thomas",
            "lastName": "Taylor",
            "gender": "Male",
            "email": "thomas.taylor_70@university.edu",
            "dateOfBirth": "1984-04-20",
            "age": 40,
            "major": "English Literature",
            "university": "Global University",
            "graduationYear": 2026,
            "gpa": 2.6,
            "creditHours": 116,
            "isInternational": false,
            "scholarshipRecipient": true,
            "phoneNumber": "(689) 122-2285"
        },
        {
            "id": 71,
            "firstName": "Carol",
            "lastName": "Garcia",
            "gender": "Female",
            "email": "carol.garcia_71@university.edu",
            "dateOfBirth": "1986-04-17",
            "age": 38,
            "major": "English Literature",
            "university": "Northern College",
            "graduationYear": 2025,
            "gpa": 3.7,
            "creditHours": 102,
            "isInternational": false,
            "scholarshipRecipient": true,
            "phoneNumber": "(453) 608-9165"
        },
        {
            "id": 72,
            "firstName": "Joseph",
            "lastName": "Rodriguez",
            "gender": "Male",
            "email": "joseph.rodriguez_72@university.edu",
            "dateOfBirth": "1985-02-26",
            "age": 39,
            "major": "Economics",
            "university": "Innovation Institute",
            "graduationYear": 2026,
            "gpa": 2.76,
            "creditHours": 49,
            "isInternational": false,
            "scholarshipRecipient": true,
            "phoneNumber": "(771) 619-9086"
        },
        {
            "id": 73,
            "firstName": "Sandra",
            "lastName": "Davis",
            "gender": "Female",
            "email": "sandra.davis_73@university.edu",
            "dateOfBirth": "1987-12-04",
            "age": 37,
            "major": "Business Administration",
            "university": "Innovation Institute",
            "graduationYear": 2024,
            "gpa": 3.47,
            "creditHours": 59,
            "isInternational": true,
            "scholarshipRecipient": true,
            "phoneNumber": "(257) 100-4502"
        },
        {
            "id": 74,
            "firstName": "Andrew",
            "lastName": "Miller",
            "gender": "Male",
            "email": "andrew.miller_74@university.edu",
            "dateOfBirth": "1986-05-10",
            "age": 38,
            "major": "International Relations",
            "university": "Tech Institute",
            "graduationYear": 2024,
            "gpa": 3.09,
            "creditHours": 114,
            "isInternational": true,
            "scholarshipRecipient": true,
            "phoneNumber": "(851) 812-9933"
        },
        {
            "id": 75,
            "firstName": "Paul",
            "lastName": "Taylor",
            "gender": "Male",
            "email": "paul.taylor_75@university.edu",
            "dateOfBirth": "1987-11-16",
            "age": 37,
            "major": "Data Science",
            "university": "Liberal Arts College",
            "graduationYear": 2024,
            "gpa": 3.9,
            "creditHours": 102,
            "isInternational": true,
            "scholarshipRecipient": true,
            "phoneNumber": "(558) 774-4093"
        },
        {
            "id": 76,
            "firstName": "Daniel",
            "lastName": "Smith",
            "gender": "Male",
            "email": "daniel.smith_76@university.edu",
            "dateOfBirth": "1984-06-25",
            "age": 40,
            "major": "Business Administration",
            "university": "Coastal State College",
            "graduationYear": 2028,
            "gpa": 3.9,
            "creditHours": 107,
            "isInternational": false,
            "scholarshipRecipient": true,
            "phoneNumber": "(906) 725-8937"
        },
        {
            "id": 77,
            "firstName": "James",
            "lastName": "Jones",
            "gender": "Male",
            "email": "james.jones_77@university.edu",
            "dateOfBirth": "1983-11-01",
            "age": 41,
            "major": "Biology",
            "university": "Innovation Institute",
            "graduationYear": 2024,
            "gpa": 2.67,
            "creditHours": 84,
            "isInternational": false,
            "scholarshipRecipient": false,
            "phoneNumber": "(841) 591-7847"
        },
        {
            "id": 78,
            "firstName": "Kenneth",
            "lastName": "Thompson",
            "gender": "Male",
            "email": "kenneth.thompson_78@university.edu",
            "dateOfBirth": "1981-07-21",
            "age": 43,
            "major": "Environmental Science",
            "university": "Central University",
            "graduationYear": 2028,
            "gpa": 2.95,
            "creditHours": 111,
            "isInternational": true,
            "scholarshipRecipient": true,
            "phoneNumber": "(679) 821-2208"
        },
        {
            "id": 79,
            "firstName": "Joseph",
            "lastName": "Brown",
            "gender": "Male",
            "email": "joseph.brown_79@university.edu",
            "dateOfBirth": "1983-05-15",
            "age": 41,
            "major": "Marketing",
            "university": "Central University",
            "graduationYear": 2025,
            "gpa": 2.58,
            "creditHours": 103,
            "isInternational": false,
            "scholarshipRecipient": true,
            "phoneNumber": "(273) 387-4304"
        },
        {
            "id": 80,
            "firstName": "Paul",
            "lastName": "White",
            "gender": "Male",
            "email": "paul.white_80@university.edu",
            "dateOfBirth": "1981-03-04",
            "age": 43,
            "major": "Engineering",
            "university": "Coastal State College",
            "graduationYear": 2025,
            "gpa": 2.82,
            "creditHours": 46,
            "isInternational": true,
            "scholarshipRecipient": false,
            "phoneNumber": "(484) 956-5299"
        },
        {
            "id": 81,
            "firstName": "Mark",
            "lastName": "Johnson",
            "gender": "Male",
            "email": "mark.johnson_81@university.edu",
            "dateOfBirth": "1987-10-09",
            "age": 37,
            "major": "English Literature",
            "university": "Metropolitan University",
            "graduationYear": 2026,
            "gpa": 3.37,
            "creditHours": 104,
            "isInternational": true,
            "scholarshipRecipient": false,
            "phoneNumber": "(697) 320-4422"
        },
        {
            "id": 82,
            "firstName": "Joseph",
            "lastName": "Rodriguez",
            "gender": "Male",
            "email": "joseph.rodriguez_82@university.edu",
            "dateOfBirth": "1982-02-09",
            "age": 42,
            "major": "Political Science",
            "university": "Tech Institute",
            "graduationYear": 2025,
            "gpa": 3.73,
            "creditHours": 40,
            "isInternational": false,
            "scholarshipRecipient": true,
            "phoneNumber": "(636) 740-1237"
        },
        {
            "id": 83,
            "firstName": "Michael",
            "lastName": "Hernandez",
            "gender": "Male",
            "email": "michael.hernandez_83@university.edu",
            "dateOfBirth": "1984-02-24",
            "age": 40,
            "major": "Data Science",
            "university": "Liberal Arts College",
            "graduationYear": 2028,
            "gpa": 3.54,
            "creditHours": 100,
            "isInternational": true,
            "scholarshipRecipient": false,
            "phoneNumber": "(681) 658-2814"
        },
        {
            "id": 84,
            "firstName": "Charles",
            "lastName": "Martinez",
            "gender": "Male",
            "email": "charles.martinez_84@university.edu",
            "dateOfBirth": "1982-08-03",
            "age": 42,
            "major": "Chemistry",
            "university": "Global University",
            "graduationYear": 2027,
            "gpa": 3.89,
            "creditHours": 33,
            "isInternational": true,
            "scholarshipRecipient": false,
            "phoneNumber": "(880) 967-9623"
        },
        {
            "id": 85,
            "firstName": "Daniel",
            "lastName": "Anderson",
            "gender": "Male",
            "email": "daniel.anderson_85@university.edu",
            "dateOfBirth": "1984-09-04",
            "age": 40,
            "major": "Graphic Design",
            "university": "Mountain View University",
            "graduationYear": 2027,
            "gpa": 2.89,
            "creditHours": 30,
            "isInternational": true,
            "scholarshipRecipient": false,
            "phoneNumber": "(857) 203-4766"
        },
        {
            "id": 86,
            "firstName": "David",
            "lastName": "Martin",
            "gender": "Male",
            "email": "david.martin_86@university.edu",
            "dateOfBirth": "1981-02-22",
            "age": 43,
            "major": "Engineering",
            "university": "Central University",
            "graduationYear": 2028,
            "gpa": 2.94,
            "creditHours": 59,
            "isInternational": true,
            "scholarshipRecipient": true,
            "phoneNumber": "(784) 704-8639"
        },
        {
            "id": 87,
            "firstName": "Jennifer",
            "lastName": "Johnson",
            "gender": "Female",
            "email": "jennifer.johnson_87@university.edu",
            "dateOfBirth": "1983-07-15",
            "age": 41,
            "major": "Engineering",
            "university": "Liberal Arts College",
            "graduationYear": 2024,
            "gpa": 3.81,
            "creditHours": 71,
            "isInternational": false,
            "scholarshipRecipient": false,
            "phoneNumber": "(424) 493-8589"
        },
        {
            "id": 88,
            "firstName": "Ashley",
            "lastName": "Davis",
            "gender": "Female",
            "email": "ashley.davis_88@university.edu",
            "dateOfBirth": "1987-04-10",
            "age": 37,
            "major": "Psychology",
            "university": "Metropolitan University",
            "graduationYear": 2027,
            "gpa": 3.44,
            "creditHours": 58,
            "isInternational": true,
            "scholarshipRecipient": false,
            "phoneNumber": "(893) 157-2563"
        },
        {
            "id": 89,
            "firstName": "Thomas",
            "lastName": "Wilson",
            "gender": "Male",
            "email": "thomas.wilson_89@university.edu",
            "dateOfBirth": "1982-11-08",
            "age": 42,
            "major": "Economics",
            "university": "Liberal Arts College",
            "graduationYear": 2026,
            "gpa": 2.98,
            "creditHours": 67,
            "isInternational": true,
            "scholarshipRecipient": false,
            "phoneNumber": "(490) 912-4522"
        },
        {
            "id": 90,
            "firstName": "John",
            "lastName": "Rodriguez",
            "gender": "Male",
            "email": "john.rodriguez_90@university.edu",
            "dateOfBirth": "1988-04-05",
            "age": 36,
            "major": "Data Science",
            "university": "Tech Institute",
            "graduationYear": 2028,
            "gpa": 3.63,
            "creditHours": 34,
            "isInternational": true,
            "scholarshipRecipient": true,
            "phoneNumber": "(381) 345-2535"
        },
        {
            "id": 91,
            "firstName": "Carol",
            "lastName": "Wilson",
            "gender": "Female",
            "email": "carol.wilson_91@university.edu",
            "dateOfBirth": "1985-08-10",
            "age": 39,
            "major": "Electrical Engineering",
            "university": "Mountain View University",
            "graduationYear": 2026,
            "gpa": 2.57,
            "creditHours": 65,
            "isInternational": false,
            "scholarshipRecipient": false,
            "phoneNumber": "(457) 159-3404"
        },
        {
            "id": 92,
            "firstName": "William",
            "lastName": "Thomas",
            "gender": "Male",
            "email": "william.thomas_92@university.edu",
            "dateOfBirth": "1988-02-27",
            "age": 36,
            "major": "Mathematics",
            "university": "Northern College",
            "graduationYear": 2027,
            "gpa": 3.57,
            "creditHours": 48,
            "isInternational": true,
            "scholarshipRecipient": true,
            "phoneNumber": "(458) 331-2015"
        },
        {
            "id": 93,
            "firstName": "Linda",
            "lastName": "Johnson",
            "gender": "Female",
            "email": "linda.johnson_93@university.edu",
            "dateOfBirth": "1982-07-20",
            "age": 42,
            "major": "Graphic Design",
            "university": "Central University",
            "graduationYear": 2025,
            "gpa": 3.16,
            "creditHours": 46,
            "isInternational": true,
            "scholarshipRecipient": true,
            "phoneNumber": "(627) 825-7250"
        },
        {
            "id": 94,
            "firstName": "Andrew",
            "lastName": "Jackson",
            "gender": "Male",
            "email": "andrew.jackson_94@university.edu",
            "dateOfBirth": "1982-02-02",
            "age": 42,
            "major": "Engineering",
            "university": "Global University",
            "graduationYear": 2026,
            "gpa": 3.25,
            "creditHours": 48,
            "isInternational": false,
            "scholarshipRecipient": false,
            "phoneNumber": "(994) 265-1675"
        },
        {
            "id": 95,
            "firstName": "John",
            "lastName": "Taylor",
            "gender": "Male",
            "email": "john.taylor_95@university.edu",
            "dateOfBirth": "1983-12-16",
            "age": 41,
            "major": "Data Science",
            "university": "State University",
            "graduationYear": 2028,
            "gpa": 2.81,
            "creditHours": 43,
            "isInternational": false,
            "scholarshipRecipient": true,
            "phoneNumber": "(754) 614-2832"
        },
        {
            "id": 96,
            "firstName": "John",
            "lastName": "Davis",
            "gender": "Male",
            "email": "john.davis_96@university.edu",
            "dateOfBirth": "1982-06-22",
            "age": 42,
            "major": "Nursing",
            "university": "Central University",
            "graduationYear": 2025,
            "gpa": 3.84,
            "creditHours": 115,
            "isInternational": true,
            "scholarshipRecipient": false,
            "phoneNumber": "(569) 471-7494"
        },
        {
            "id": 97,
            "firstName": "John",
            "lastName": "Taylor",
            "gender": "Male",
            "email": "john.taylor_97@university.edu",
            "dateOfBirth": "1988-03-12",
            "age": 36,
            "major": "International Relations",
            "university": "Coastal State College",
            "graduationYear": 2025,
            "gpa": 3.29,
            "creditHours": 36,
            "isInternational": false,
            "scholarshipRecipient": false,
            "phoneNumber": "(290) 334-7012"
        },
        {
            "id": 98,
            "firstName": "Matthew",
            "lastName": "Anderson",
            "gender": "Male",
            "email": "matthew.anderson_98@university.edu",
            "dateOfBirth": "1984-03-09",
            "age": 40,
            "major": "Electrical Engineering",
            "university": "Metropolitan University",
            "graduationYear": 2028,
            "gpa": 3.07,
            "creditHours": 102,
            "isInternational": false,
            "scholarshipRecipient": false,
            "phoneNumber": "(231) 839-2804"
        },
        {
            "id": 99,
            "firstName": "Margaret",
            "lastName": "Anderson",
            "gender": "Female",
            "email": "margaret.anderson_99@university.edu",
            "dateOfBirth": "1988-03-25",
            "age": 36,
            "major": "Computer Science",
            "university": "Mountain View University",
            "graduationYear": 2025,
            "gpa": 3.47,
            "creditHours": 112,
            "isInternational": false,
            "scholarshipRecipient": false,
            "phoneNumber": "(383) 241-4768"
        },
        {
            "id": 100,
            "firstName": "Paul",
            "lastName": "Wilson",
            "gender": "Male",
            "email": "paul.wilson_100@university.edu",
            "dateOfBirth": "1985-10-01",
            "age": 39,
            "major": "Data Science",
            "university": "Liberal Arts College",
            "graduationYear": 2025,
            "gpa": 3.7,
            "creditHours": 46,
            "isInternational": false,
            "scholarshipRecipient": false,
            "phoneNumber": "(750) 270-1719"
        },
        {
            "id": 101,
            "firstName": "Karen",
            "lastName": "Brown",
            "gender": "Female",
            "email": "karen.brown_101@university.edu",
            "dateOfBirth": "1986-02-28",
            "age": 38,
            "major": "Psychology",
            "university": "State University",
            "graduationYear": 2026,
            "gpa": 2.8,
            "creditHours": 35,
            "isInternational": true,
            "scholarshipRecipient": false,
            "phoneNumber": "(724) 515-7205"
        },
        {
            "id": 102,
            "firstName": "Jessica",
            "lastName": "Johnson",
            "gender": "Female",
            "email": "jessica.johnson_102@university.edu",
            "dateOfBirth": "1986-08-10",
            "age": 38,
            "major": "Engineering",
            "university": "Mountain View University",
            "graduationYear": 2028,
            "gpa": 3.24,
            "creditHours": 103,
            "isInternational": false,
            "scholarshipRecipient": false,
            "phoneNumber": "(697) 652-4094"
        },
        {
            "id": 103,
            "firstName": "Matthew",
            "lastName": "Anderson",
            "gender": "Male",
            "email": "matthew.anderson_103@university.edu",
            "dateOfBirth": "1981-11-13",
            "age": 43,
            "major": "Marketing",
            "university": "Central University",
            "graduationYear": 2025,
            "gpa": 3.43,
            "creditHours": 39,
            "isInternational": false,
            "scholarshipRecipient": false,
            "phoneNumber": "(350) 724-7786"
        },
        {
            "id": 104,
            "firstName": "Charles",
            "lastName": "Smith",
            "gender": "Male",
            "email": "charles.smith_104@university.edu",
            "dateOfBirth": "1988-05-06",
            "age": 36,
            "major": "Mechanical Engineering",
            "university": "Metropolitan University",
            "graduationYear": 2025,
            "gpa": 3.34,
            "creditHours": 85,
            "isInternational": true,
            "scholarshipRecipient": true,
            "phoneNumber": "(446) 461-6898"
        },
        {
            "id": 105,
            "firstName": "Donna",
            "lastName": "Thomas",
            "gender": "Female",
            "email": "donna.thomas_105@university.edu",
            "dateOfBirth": "1982-03-18",
            "age": 42,
            "major": "Physics",
            "university": "Mountain View University",
            "graduationYear": 2025,
            "gpa": 2.97,
            "creditHours": 42,
            "isInternational": false,
            "scholarshipRecipient": true,
            "phoneNumber": "(475) 687-5667"
        },
        {
            "id": 106,
            "firstName": "Nancy",
            "lastName": "Taylor",
            "gender": "Female",
            "email": "nancy.taylor_106@university.edu",
            "dateOfBirth": "1981-01-02",
            "age": 43,
            "major": "International Relations",
            "university": "Northern College",
            "graduationYear": 2028,
            "gpa": 3.47,
            "creditHours": 67,
            "isInternational": false,
            "scholarshipRecipient": false,
            "phoneNumber": "(250) 323-2860"
        },
        {
            "id": 107,
            "firstName": "Linda",
            "lastName": "Martin",
            "gender": "Female",
            "email": "linda.martin_107@university.edu",
            "dateOfBirth": "1985-03-01",
            "age": 39,
            "major": "Physics",
            "university": "Global University",
            "graduationYear": 2024,
            "gpa": 2.9,
            "creditHours": 62,
            "isInternational": true,
            "scholarshipRecipient": false,
            "phoneNumber": "(288) 342-3045"
        },
        {
            "id": 108,
            "firstName": "Linda",
            "lastName": "Martin",
            "gender": "Female",
            "email": "linda.martin_108@university.edu",
            "dateOfBirth": "1985-10-13",
            "age": 39,
            "major": "Electrical Engineering",
            "university": "Northern College",
            "graduationYear": 2028,
            "gpa": 3.67,
            "creditHours": 65,
            "isInternational": false,
            "scholarshipRecipient": true,
            "phoneNumber": "(630) 723-8453"
        },
        {
            "id": 109,
            "firstName": "Barbara",
            "lastName": "Davis",
            "gender": "Female",
            "email": "barbara.davis_109@university.edu",
            "dateOfBirth": "1981-12-09",
            "age": 43,
            "major": "Physics",
            "university": "Coastal State College",
            "graduationYear": 2025,
            "gpa": 3.41,
            "creditHours": 39,
            "isInternational": false,
            "scholarshipRecipient": true,
            "phoneNumber": "(419) 382-8119"
        },
        {
            "id": 110,
            "firstName": "Donna",
            "lastName": "Jackson",
            "gender": "Female",
            "email": "donna.jackson_110@university.edu",
            "dateOfBirth": "1981-06-11",
            "age": 43,
            "major": "Engineering",
            "university": "Coastal State College",
            "graduationYear": 2028,
            "gpa": 3.19,
            "creditHours": 88,
            "isInternational": true,
            "scholarshipRecipient": true,
            "phoneNumber": "(617) 272-8559"
        },
        {
            "id": 111,
            "firstName": "Linda",
            "lastName": "Hernandez",
            "gender": "Female",
            "email": "linda.hernandez_111@university.edu",
            "dateOfBirth": "1988-08-23",
            "age": 36,
            "major": "Mathematics",
            "university": "Metropolitan University",
            "graduationYear": 2025,
            "gpa": 2.69,
            "creditHours": 51,
            "isInternational": false,
            "scholarshipRecipient": false,
            "phoneNumber": "(639) 265-7542"
        },
        {
            "id": 112,
            "firstName": "Kenneth",
            "lastName": "Martin",
            "gender": "Male",
            "email": "kenneth.martin_112@university.edu",
            "dateOfBirth": "1985-03-23",
            "age": 39,
            "major": "English Literature",
            "university": "Central University",
            "graduationYear": 2027,
            "gpa": 3.34,
            "creditHours": 39,
            "isInternational": true,
            "scholarshipRecipient": true,
            "phoneNumber": "(428) 308-7907"
        },
        {
            "id": 113,
            "firstName": "Emily",
            "lastName": "Williams",
            "gender": "Female",
            "email": "emily.williams_113@university.edu",
            "dateOfBirth": "1983-02-25",
            "age": 41,
            "major": "Environmental Science",
            "university": "Mountain View University",
            "graduationYear": 2024,
            "gpa": 2.76,
            "creditHours": 89,
            "isInternational": true,
            "scholarshipRecipient": false,
            "phoneNumber": "(318) 674-6934"
        },
        {
            "id": 114,
            "firstName": "Elizabeth",
            "lastName": "Martin",
            "gender": "Female",
            "email": "elizabeth.martin_114@university.edu",
            "dateOfBirth": "1987-11-24",
            "age": 37,
            "major": "Mechanical Engineering",
            "university": "State University",
            "graduationYear": 2027,
            "gpa": 2.88,
            "creditHours": 62,
            "isInternational": false,
            "scholarshipRecipient": false,
            "phoneNumber": "(916) 824-9871"
        },
        {
            "id": 115,
            "firstName": "Carol",
            "lastName": "Thompson",
            "gender": "Female",
            "email": "carol.thompson_115@university.edu",
            "dateOfBirth": "1984-12-09",
            "age": 40,
            "major": "Chemistry",
            "university": "Liberal Arts College",
            "graduationYear": 2026,
            "gpa": 2.71,
            "creditHours": 88,
            "isInternational": false,
            "scholarshipRecipient": true,
            "phoneNumber": "(942) 986-3937"
        },
        {
            "id": 116,
            "firstName": "Paul",
            "lastName": "Thomas",
            "gender": "Male",
            "email": "paul.thomas_116@university.edu",
            "dateOfBirth": "1983-07-08",
            "age": 41,
            "major": "Political Science",
            "university": "Metropolitan University",
            "graduationYear": 2025,
            "gpa": 3.35,
            "creditHours": 114,
            "isInternational": false,
            "scholarshipRecipient": true,
            "phoneNumber": "(469) 198-3295"
        },
        {
            "id": 117,
            "firstName": "Andrew",
            "lastName": "Anderson",
            "gender": "Male",
            "email": "andrew.anderson_117@university.edu",
            "dateOfBirth": "1985-06-26",
            "age": 39,
            "major": "Mathematics",
            "university": "Global University",
            "graduationYear": 2028,
            "gpa": 2.79,
            "creditHours": 81,
            "isInternational": true,
            "scholarshipRecipient": true,
            "phoneNumber": "(596) 983-3307"
        },
        {
            "id": 118,
            "firstName": "Sarah",
            "lastName": "Garcia",
            "gender": "Female",
            "email": "sarah.garcia_118@university.edu",
            "dateOfBirth": "1982-01-23",
            "age": 42,
            "major": "Graphic Design",
            "university": "State University",
            "graduationYear": 2028,
            "gpa": 2.74,
            "creditHours": 94,
            "isInternational": true,
            "scholarshipRecipient": false,
            "phoneNumber": "(396) 135-1063"
        },
        {
            "id": 119,
            "firstName": "Kimberly",
            "lastName": "Davis",
            "gender": "Female",
            "email": "kimberly.davis_119@university.edu",
            "dateOfBirth": "1988-06-18",
            "age": 36,
            "major": "International Relations",
            "university": "Central University",
            "graduationYear": 2027,
            "gpa": 2.92,
            "creditHours": 114,
            "isInternational": true,
            "scholarshipRecipient": false,
            "phoneNumber": "(448) 583-3604"
        },
        {
            "id": 120,
            "firstName": "Jennifer",
            "lastName": "Moore",
            "gender": "Female",
            "email": "jennifer.moore_120@university.edu",
            "dateOfBirth": "1981-08-25",
            "age": 43,
            "major": "Electrical Engineering",
            "university": "Northern College",
            "graduationYear": 2027,
            "gpa": 2.62,
            "creditHours": 70,
            "isInternational": false,
            "scholarshipRecipient": false,
            "phoneNumber": "(438) 191-4976"
        },
        {
            "id": 121,
            "firstName": "Joseph",
            "lastName": "Garcia",
            "gender": "Male",
            "email": "joseph.garcia_121@university.edu",
            "dateOfBirth": "1987-07-25",
            "age": 37,
            "major": "English Literature",
            "university": "Mountain View University",
            "graduationYear": 2028,
            "gpa": 2.82,
            "creditHours": 58,
            "isInternational": true,
            "scholarshipRecipient": true,
            "phoneNumber": "(589) 521-3707"
        },
        {
            "id": 122,
            "firstName": "John",
            "lastName": "Garcia",
            "gender": "Male",
            "email": "john.garcia_122@university.edu",
            "dateOfBirth": "1983-05-01",
            "age": 41,
            "major": "Nursing",
            "university": "Coastal State College",
            "graduationYear": 2027,
            "gpa": 2.59,
            "creditHours": 54,
            "isInternational": true,
            "scholarshipRecipient": true,
            "phoneNumber": "(761) 934-7845"
        },
        {
            "id": 123,
            "firstName": "Charles",
            "lastName": "Davis",
            "gender": "Male",
            "email": "charles.davis_123@university.edu",
            "dateOfBirth": "1981-05-17",
            "age": 43,
            "major": "Graphic Design",
            "university": "Global University",
            "graduationYear": 2027,
            "gpa": 2.54,
            "creditHours": 94,
            "isInternational": true,
            "scholarshipRecipient": true,
            "phoneNumber": "(365) 448-9031"
        },
        {
            "id": 124,
            "firstName": "Lisa",
            "lastName": "Brown",
            "gender": "Female",
            "email": "lisa.brown_124@university.edu",
            "dateOfBirth": "1984-12-13",
            "age": 40,
            "major": "Environmental Science",
            "university": "Tech Institute",
            "graduationYear": 2028,
            "gpa": 3.38,
            "creditHours": 40,
            "isInternational": true,
            "scholarshipRecipient": true,
            "phoneNumber": "(419) 892-8364"
        },
        {
            "id": 125,
            "firstName": "James",
            "lastName": "Anderson",
            "gender": "Male",
            "email": "james.anderson_125@university.edu",
            "dateOfBirth": "1988-07-18",
            "age": 36,
            "major": "Chemistry",
            "university": "Coastal State College",
            "graduationYear": 2024,
            "gpa": 3.88,
            "creditHours": 105,
            "isInternational": false,
            "scholarshipRecipient": false,
            "phoneNumber": "(344) 526-4322"
        },
        {
            "id": 126,
            "firstName": "Thomas",
            "lastName": "Hernandez",
            "gender": "Male",
            "email": "thomas.hernandez_126@university.edu",
            "dateOfBirth": "1983-03-01",
            "age": 41,
            "major": "Political Science",
            "university": "Global University",
            "graduationYear": 2028,
            "gpa": 2.75,
            "creditHours": 41,
            "isInternational": false,
            "scholarshipRecipient": true,
            "phoneNumber": "(886) 107-6648"
        },
        {
            "id": 127,
            "firstName": "Daniel",
            "lastName": "Williams",
            "gender": "Male",
            "email": "daniel.williams_127@university.edu",
            "dateOfBirth": "1987-05-12",
            "age": 37,
            "major": "English Literature",
            "university": "Metropolitan University",
            "graduationYear": 2025,
            "gpa": 3.29,
            "creditHours": 47,
            "isInternational": false,
            "scholarshipRecipient": false,
            "phoneNumber": "(453) 628-1838"
        },
        {
            "id": 128,
            "firstName": "Joseph",
            "lastName": "Smith",
            "gender": "Male",
            "email": "joseph.smith_128@university.edu",
            "dateOfBirth": "1988-05-24",
            "age": 36,
            "major": "Communications",
            "university": "Innovation Institute",
            "graduationYear": 2024,
            "gpa": 3.85,
            "creditHours": 48,
            "isInternational": false,
            "scholarshipRecipient": false,
            "phoneNumber": "(467) 247-4076"
        },
        {
            "id": 129,
            "firstName": "Donald",
            "lastName": "Garcia",
            "gender": "Male",
            "email": "donald.garcia_129@university.edu",
            "dateOfBirth": "1988-02-25",
            "age": 36,
            "major": "Environmental Science",
            "university": "Global University",
            "graduationYear": 2025,
            "gpa": 2.55,
            "creditHours": 47,
            "isInternational": false,
            "scholarshipRecipient": true,
            "phoneNumber": "(830) 462-2150"
        },
        {
            "id": 130,
            "firstName": "Sandra",
            "lastName": "Garcia",
            "gender": "Female",
            "email": "sandra.garcia_130@university.edu",
            "dateOfBirth": "1988-08-02",
            "age": 36,
            "major": "Graphic Design",
            "university": "Global University",
            "graduationYear": 2026,
            "gpa": 2.74,
            "creditHours": 108,
            "isInternational": false,
            "scholarshipRecipient": true,
            "phoneNumber": "(221) 946-1585"
        },
        {
            "id": 131,
            "firstName": "Donald",
            "lastName": "Smith",
            "gender": "Male",
            "email": "donald.smith_131@university.edu",
            "dateOfBirth": "1982-10-05",
            "age": 42,
            "major": "Biology",
            "university": "Global University",
            "graduationYear": 2026,
            "gpa": 2.75,
            "creditHours": 53,
            "isInternational": true,
            "scholarshipRecipient": true,
            "phoneNumber": "(592) 349-8534"
        },
        {
            "id": 132,
            "firstName": "Linda",
            "lastName": "Martinez",
            "gender": "Female",
            "email": "linda.martinez_132@university.edu",
            "dateOfBirth": "1983-04-01",
            "age": 41,
            "major": "Engineering",
            "university": "Liberal Arts College",
            "graduationYear": 2025,
            "gpa": 2.9,
            "creditHours": 109,
            "isInternational": true,
            "scholarshipRecipient": true,
            "phoneNumber": "(529) 648-1894"
        },
        {
            "id": 133,
            "firstName": "Carol",
            "lastName": "Davis",
            "gender": "Female",
            "email": "carol.davis_133@university.edu",
            "dateOfBirth": "1984-12-04",
            "age": 40,
            "major": "Psychology",
            "university": "Coastal State College",
            "graduationYear": 2026,
            "gpa": 2.55,
            "creditHours": 57,
            "isInternational": false,
            "scholarshipRecipient": false,
            "phoneNumber": "(781) 199-2032"
        },
        {
            "id": 134,
            "firstName": "John",
            "lastName": "Davis",
            "gender": "Male",
            "email": "john.davis_134@university.edu",
            "dateOfBirth": "1988-07-15",
            "age": 36,
            "major": "Economics",
            "university": "Global University",
            "graduationYear": 2026,
            "gpa": 2.95,
            "creditHours": 98,
            "isInternational": true,
            "scholarshipRecipient": false,
            "phoneNumber": "(449) 465-9474"
        },
        {
            "id": 135,
            "firstName": "Sandra",
            "lastName": "Miller",
            "gender": "Female",
            "email": "sandra.miller_135@university.edu",
            "dateOfBirth": "1986-01-05",
            "age": 38,
            "major": "Electrical Engineering",
            "university": "State University",
            "graduationYear": 2024,
            "gpa": 2.82,
            "creditHours": 52,
            "isInternational": false,
            "scholarshipRecipient": true,
            "phoneNumber": "(327) 201-3751"
        },
        {
            "id": 136,
            "firstName": "Christopher",
            "lastName": "Wilson",
            "gender": "Male",
            "email": "christopher.wilson_136@university.edu",
            "dateOfBirth": "1982-05-19",
            "age": 42,
            "major": "Economics",
            "university": "Metropolitan University",
            "graduationYear": 2025,
            "gpa": 3.8,
            "creditHours": 58,
            "isInternational": true,
            "scholarshipRecipient": false,
            "phoneNumber": "(459) 168-6593"
        },
        {
            "id": 137,
            "firstName": "Daniel",
            "lastName": "Wilson",
            "gender": "Male",
            "email": "daniel.wilson_137@university.edu",
            "dateOfBirth": "1981-09-22",
            "age": 43,
            "major": "Marketing",
            "university": "Coastal State College",
            "graduationYear": 2024,
            "gpa": 2.62,
            "creditHours": 36,
            "isInternational": false,
            "scholarshipRecipient": true,
            "phoneNumber": "(462) 357-1983"
        },
        {
            "id": 138,
            "firstName": "Lisa",
            "lastName": "Johnson",
            "gender": "Female",
            "email": "lisa.johnson_138@university.edu",
            "dateOfBirth": "1981-03-14",
            "age": 43,
            "major": "Business Administration",
            "university": "Global University",
            "graduationYear": 2026,
            "gpa": 2.65,
            "creditHours": 91,
            "isInternational": false,
            "scholarshipRecipient": false,
            "phoneNumber": "(256) 692-5575"
        },
        {
            "id": 139,
            "firstName": "Daniel",
            "lastName": "Moore",
            "gender": "Male",
            "email": "daniel.moore_139@university.edu",
            "dateOfBirth": "1986-02-06",
            "age": 38,
            "major": "Marketing",
            "university": "Central University",
            "graduationYear": 2025,
            "gpa": 3.37,
            "creditHours": 42,
            "isInternational": true,
            "scholarshipRecipient": true,
            "phoneNumber": "(553) 544-2759"
        },
        {
            "id": 140,
            "firstName": "Linda",
            "lastName": "Moore",
            "gender": "Female",
            "email": "linda.moore_140@university.edu",
            "dateOfBirth": "1984-05-23",
            "age": 40,
            "major": "Political Science",
            "university": "Innovation Institute",
            "graduationYear": 2025,
            "gpa": 2.53,
            "creditHours": 76,
            "isInternational": false,
            "scholarshipRecipient": true,
            "phoneNumber": "(909) 827-6376"
        },
        {
            "id": 141,
            "firstName": "Matthew",
            "lastName": "Moore",
            "gender": "Male",
            "email": "matthew.moore_141@university.edu",
            "dateOfBirth": "1983-10-01",
            "age": 41,
            "major": "Chemistry",
            "university": "Metropolitan University",
            "graduationYear": 2025,
            "gpa": 3.1,
            "creditHours": 47,
            "isInternational": false,
            "scholarshipRecipient": true,
            "phoneNumber": "(736) 479-5838"
        },
        {
            "id": 142,
            "firstName": "Michael",
            "lastName": "Hernandez",
            "gender": "Male",
            "email": "michael.hernandez_142@university.edu",
            "dateOfBirth": "1986-11-24",
            "age": 38,
            "major": "Mechanical Engineering",
            "university": "Northern College",
            "graduationYear": 2025,
            "gpa": 3.31,
            "creditHours": 39,
            "isInternational": true,
            "scholarshipRecipient": true,
            "phoneNumber": "(673) 474-9708"
        },
        {
            "id": 143,
            "firstName": "Elizabeth",
            "lastName": "White",
            "gender": "Female",
            "email": "elizabeth.white_143@university.edu",
            "dateOfBirth": "1985-07-19",
            "age": 39,
            "major": "Environmental Science",
            "university": "Northern College",
            "graduationYear": 2028,
            "gpa": 3.76,
            "creditHours": 106,
            "isInternational": true,
            "scholarshipRecipient": false,
            "phoneNumber": "(679) 174-1546"
        },
        {
            "id": 144,
            "firstName": "Charles",
            "lastName": "Smith",
            "gender": "Male",
            "email": "charles.smith_144@university.edu",
            "dateOfBirth": "1982-03-13",
            "age": 42,
            "major": "Political Science",
            "university": "Global University",
            "graduationYear": 2027,
            "gpa": 2.91,
            "creditHours": 60,
            "isInternational": true,
            "scholarshipRecipient": false,
            "phoneNumber": "(297) 315-4989"
        },
        {
            "id": 145,
            "firstName": "Paul",
            "lastName": "Moore",
            "gender": "Male",
            "email": "paul.moore_145@university.edu",
            "dateOfBirth": "1984-11-12",
            "age": 40,
            "major": "Physics",
            "university": "Central University",
            "graduationYear": 2025,
            "gpa": 3.13,
            "creditHours": 68,
            "isInternational": true,
            "scholarshipRecipient": true,
            "phoneNumber": "(427) 366-7870"
        },
        {
            "id": 146,
            "firstName": "John",
            "lastName": "Jones",
            "gender": "Male",
            "email": "john.jones_146@university.edu",
            "dateOfBirth": "1982-04-18",
            "age": 42,
            "major": "Biology",
            "university": "Metropolitan University",
            "graduationYear": 2028,
            "gpa": 3.16,
            "creditHours": 42,
            "isInternational": false,
            "scholarshipRecipient": false,
            "phoneNumber": "(580) 844-3651"
        },
        {
            "id": 147,
            "firstName": "Jessica",
            "lastName": "Martin",
            "gender": "Female",
            "email": "jessica.martin_147@university.edu",
            "dateOfBirth": "1987-02-15",
            "age": 37,
            "major": "Nursing",
            "university": "Innovation Institute",
            "graduationYear": 2026,
            "gpa": 3.44,
            "creditHours": 30,
            "isInternational": true,
            "scholarshipRecipient": false,
            "phoneNumber": "(401) 269-3784"
        },
        {
            "id": 148,
            "firstName": "Charles",
            "lastName": "Thomas",
            "gender": "Male",
            "email": "charles.thomas_148@university.edu",
            "dateOfBirth": "1987-12-15",
            "age": 37,
            "major": "Electrical Engineering",
            "university": "State University",
            "graduationYear": 2028,
            "gpa": 2.99,
            "creditHours": 40,
            "isInternational": false,
            "scholarshipRecipient": false,
            "phoneNumber": "(866) 451-1653"
        },
        {
            "id": 149,
            "firstName": "Christopher",
            "lastName": "Rodriguez",
            "gender": "Male",
            "email": "christopher.rodriguez_149@university.edu",
            "dateOfBirth": "1983-04-17",
            "age": 41,
            "major": "Graphic Design",
            "university": "Central University",
            "graduationYear": 2027,
            "gpa": 2.76,
            "creditHours": 98,
            "isInternational": true,
            "scholarshipRecipient": false,
            "phoneNumber": "(769) 378-6781"
        },
        {
            "id": 150,
            "firstName": "Lisa",
            "lastName": "Jackson",
            "gender": "Female",
            "email": "lisa.jackson_150@university.edu",
            "dateOfBirth": "1984-09-28",
            "age": 40,
            "major": "Nursing",
            "university": "Central University",
            "graduationYear": 2026,
            "gpa": 3.73,
            "creditHours": 103,
            "isInternational": true,
            "scholarshipRecipient": false,
            "phoneNumber": "(967) 482-9364"
        }
    ]
}